setup.cfg
setup.py
yibai/__init__.py
yibai/api/HttpUtils.py
yibai/api/Yibai.py
yibai/api/__init__.py
yibai_sms_python_sdk.egg-info/PKG-INFO
yibai_sms_python_sdk.egg-info/SOURCES.txt
yibai_sms_python_sdk.egg-info/dependency_links.txt
yibai_sms_python_sdk.egg-info/requires.txt
yibai_sms_python_sdk.egg-info/top_level.txt