Metadata-Version: 1.0
Name: yibai-sms-python-sdk
Version: 1.0.0
Summary: yibai python sdk
Home-page: UNKNOWN
Author: shomop
Author-email: lanran@shomop.com
License: MIT
Keywords: yibai,sms,sdk
Platform: any
